pyproject_info/__init__.py
pyproject_info/main.py
pyproject_info-0.2.0.dist-info/METADATA
pyproject_info-0.2.0.dist-info/WHEEL
pyproject_info-0.2.0.dist-info/RECORD
